LICENSE.txt
MANIFEST.in
README.rst
setup.py
blacklist/__init__.py
blacklist/admin.py
blacklist/apps.py
blacklist/models.py
blacklist/tests.py
blacklist/utils.py
blacklist/locale/ru/LC_MESSAGES/django.mo
blacklist/locale/ru/LC_MESSAGES/django.po
blacklist/management/__init__.py
blacklist/management/commands/__init__.py
blacklist/management/commands/blacklist-update_cache.py
blacklist/management/commands/remove_request_logs.py
blacklist/migrations/0001_initial.py
blacklist/migrations/0002_auto_20150721_0514.py
blacklist/migrations/0003_auto_20151016_0541.py
blacklist/migrations/0004_auto_20151106_1006.py
blacklist/migrations/0005_auto_20151111_0612.py
blacklist/migrations/__init__.py
blacklist/templates/blacklist/email_notification.tmpl.html
django_simple_blacklist.egg-info/PKG-INFO
django_simple_blacklist.egg-info/SOURCES.txt
django_simple_blacklist.egg-info/dependency_links.txt
django_simple_blacklist.egg-info/requires.txt
django_simple_blacklist.egg-info/top_level.txt